priority_memory/__init__.py
priority_memory/fast_memory_buff.py
priority_memory/index_priority_queue.py
priority_memory/priority_memory.py
priority_memory-0.0.1.dist-info/METADATA
priority_memory-0.0.1.dist-info/RECORD
priority_memory-0.0.1.dist-info/WHEEL
priority_memory-0.0.1.dist-info/top_level.txt
priority_memory_buffer/__init__.py
priority_memory_buffer/fast_memory_buff.py
priority_memory_buffer/index_priority_queue.py
