Metadata-Version: 2.1
Name: priority-memory
Version: 0.0.1
Summary: A priority sampling tool.
Home-page: https://github.com/rem2016/priority_memory_buffer
Author: Zixuan Chen
Author-email: remch183@outlook.com
License: UNKNOWN
Platform: UNKNOWN
Classifier: Programming Language :: Python :: 3
Classifier: License :: OSI Approved :: Apache Software License
Classifier: Operating System :: OS Independent
